{
  "name": "Mr. E",
  "size": {
    "width": 2,
    "height": 2,
  },
  "properties": [
    "player"
  ],
  "property_values": {
    "player": {
      "hitbox": {
        "x_offset": 0.25,
        "y_offset": 0,
        "width": 1.5,
        "height": 1.5,
      },
      "speed": 5,
      "texture": {
        "idle_frames": 2,
        "idle_frame_delay_ms": 1000,
        "move_frames": 4,
        "move_frame_delay_ms": 100,
        "frame_width": 32,
        "frame_height": 32,
      }
    }
  },
  "texture": "rat.png",
  "render_priority": 5,
}
